Metadata-Version: 2.1
Name: f5-tts-mlx-quantized
Version: 0.1.1
Summary: F5-TTS - MLX
Author-email: Alan Dao <contact@alandao.net>
License: MIT
Project-URL: Homepage, https://github.com/tikikun/f5-tts-mlx-quantized
Keywords: artificial intelligence,asr,audio-generation,deep learning,transformers,text-to-speech
Classifier: Development Status :: 4 - Beta
Classifier: Intended Audience :: Developers
Classifier: Topic :: Scientific/Engineering :: Artificial Intelligence
Classifier: License :: OSI Approved :: MIT License
Classifier: Programming Language :: Python :: 3.9
Requires-Python: >=3.9
License-File: LICENSE
Requires-Dist: einops
Requires-Dist: einx
Requires-Dist: jieba
Requires-Dist: huggingface_hub
Requires-Dist: mlx>=0.18.1
Requires-Dist: numpy
Requires-Dist: pypinyin
Requires-Dist: setuptools
Requires-Dist: sounddevice
Requires-Dist: soundfile
Requires-Dist: tqdm
Requires-Dist: vocos-mlx
